pangu.py
pangu-4.0.6.1.dist-info/LICENSE
pangu-4.0.6.1.dist-info/METADATA
pangu-4.0.6.1.dist-info/WHEEL
pangu-4.0.6.1.dist-info/entry_points.txt
pangu-4.0.6.1.dist-info/top_level.txt
pangu-4.0.6.1.dist-info/RECORD
